Metadata-Version: 1.1
Name: diligence
Version: 0.0.0.0
Summary: a package for test
Home-page: UNKNOWN
Author: AXEwiges
Author-email: syrupcake@protonmail.com
License: MIT
Platform: UNKNOWN
Classifier: License :: OSI Approved :: MIT License
Classifier: Programming Language :: Python
Classifier: Programming Language :: Python :: 3
Classifier: Programming Language :: Python :: 3.8
Classifier: Programming Language :: Python :: 3.9
Classifier: Programming Language :: Python :: 3.10
